doonfraction/__init__.py
doonfraction/doonfraction.py
doonfraction-1.0.2.dist-info/METADATA
doonfraction-1.0.2.dist-info/WHEEL
doonfraction-1.0.2.dist-info/entry_points.txt
doonfraction-1.0.2.dist-info/top_level.txt
doonfraction-1.0.2.dist-info/RECORD
