Metadata-Version: 2.1
Name: doonfraction
Version: 1.0.2
Summary: A Python class for working with fractions
Author: Somil
Author-email: iamsomilsharma@email.com
License: MIT
